package_PyJsonEntity/PyJsonEntity.py
package_PyJsonEntity/__init__.py
package_PyJsonEntity-1.0.1.dist-info/LICENSE
package_PyJsonEntity-1.0.1.dist-info/METADATA
package_PyJsonEntity-1.0.1.dist-info/WHEEL
package_PyJsonEntity-1.0.1.dist-info/top_level.txt
package_PyJsonEntity-1.0.1.dist-info/RECORD
