Metadata-Version: 2.1
Name: package-PyJsonEntity
Version: 1.0.1
Summary: A Json Encoder/Decoder
Home-page: https://mp.weixin.qq.com/s/9FQ-Tun5FbpBepBAsdY62w
Author: Bit
Author-email: crack22@qq.com
License: MIT License
Platform: all
Classifier: Intended Audience :: Developers
Classifier: Operating System :: OS Independent
Classifier: Natural Language :: Chinese (Simplified)
Classifier: Programming Language :: Python
Classifier: Programming Language :: Python :: 3
Classifier: Programming Language :: Python :: 3.5
Classifier: Programming Language :: Python :: 3.6
Classifier: Programming Language :: Python :: 3.7
Classifier: Programming Language :: Python :: 3.8
Classifier: Topic :: Software Development :: Libraries
License-File: LICENSE
